gee_biophys/__init__.py
gee_biophys/cli.py
gee_biophys/config.py
gee_biophys/s2_export.py
gee_biophys/s2_input.py
gee_biophys/s2_predict.py
gee_biophys/utils.py
gee_biophys/utils_predict.py
gee_biophys/models/__init__.py
gee_biophys/models/s2biophys.py
gee_biophys/models/sl2p.py
gee_biophys/models/utils_s2biophys.py
gee_biophys/models/sl2p_params/LAI-estimation_SL2P_Corrected_LeafToolBox.json
gee_biophys/models/sl2p_params/LAI-uncertainty_SL2P_Corrected_LeafToolBox.json
gee_biophys/models/sl2p_params/fAPAR-estimation_SL2P_Corrected_LeafToolBox.json
gee_biophys/models/sl2p_params/fAPAR-uncertainty_SL2P_Corrected_LeafToolBox.json
gee_biophys/models/sl2p_params/fCOVER-estimation_SL2P_Corrected_LeafToolBox.json
gee_biophys/models/sl2p_params/fCOVER-uncertainty_SL2P_Corrected_LeafToolBox.json
gee_biophys-1.3.0.dist-info/licenses/LICENSE
train_pipeline/__init__.py
train_pipeline/utilsTraining.py
gee_biophys-1.3.0.dist-info/METADATA
gee_biophys-1.3.0.dist-info/WHEEL
gee_biophys-1.3.0.dist-info/entry_points.txt
gee_biophys-1.3.0.dist-info/top_level.txt
gee_biophys-1.3.0.dist-info/RECORD
