Metadata-Version: 2.4
Name: gee-biophys
Version: 1.3.0
Summary: Custom time-series export of LAIe/FAPAR/FCOVER with YAML params.
Author-email: Felix Specker <felix.specker@wsl.ch>
License: MIT
Requires-Python: >=3.11
License-File: LICENSE
Requires-Dist: earthengine-api>=1.6.15
Requires-Dist: geojson>=3.2.0
Requires-Dist: loguru>=0.7.3
Requires-Dist: numpy
Requires-Dist: pandas>=2.3.3
Requires-Dist: pydantic>=2.12.4
Requires-Dist: python-dateutil>=2.9.0.post0
Requires-Dist: pyyaml>=6.0.3
Requires-Dist: scikit-learn==1.7.2
Requires-Dist: typer>=0.12.0
Dynamic: license-file
